pykrusch/__init__.py
pykrusch/config.py
pykrusch/dist.py
pykrusch/figureControl.py
pykrusch/main.py
pykrusch/param.py
pykrusch/graphviz/distrogramsMPL.py
pykrusch/graphviz/latexText.py
pykrusch/graphviz/pgvHTML.py
pykrusch/parsePymc/createGraph.py
pykrusch/parsePymc/deterministicVariable.py
pykrusch/parsePymc/randomVariable.py
pykrusch-0.1.2.dist-info/METADATA
pykrusch-0.1.2.dist-info/WHEEL
pykrusch-0.1.2.dist-info/entry_points.txt
pykrusch-0.1.2.dist-info/RECORD
