Metadata-Version: 2.1
Name: pykrusch
Version: 0.1.2
Summary: A python package for visualizing Bayesian model structure.
Author-email: Pierson Browne <pbrowne@uwaterloo.ca>
Requires-Python: >=3.7
Requires-Dist: arviz
Requires-Dist: click
Requires-Dist: matplotlib
Requires-Dist: numpy
Requires-Dist: pillow
Requires-Dist: pydot
Requires-Dist: pygraphviz
Requires-Dist: pymc
Requires-Dist: pytensor
Requires-Dist: scipy
